{
  "w-avatar": {
    "style": {
      "wrap": {
        "default": {
          "$value": "{bg.weak}",
          "$type": "color"
        }
      },
      "icon": {
        "default": {
          "$value": "{icon.medium}",
          "$type": "color"
        }
      },
      "label": {
        "default": {
          "$value": "{text.strongest}",
          "$type": "color"
        }
      },
      "stroke": {
        "default": {
          "$value": "{stroke.weakest}",
          "$type": "color"
        }
      },
      "shadow": {
        "default": {
          "$value": {
            "x": "{fx.axis.none}",
            "y": "{fx.axis.25}",
            "blur": "{fx.blur.25}",
            "spread": "{fx.blur.none}",
            "color": "{bg.shadow.weak}",
            "type": "innerShadow"
          },
          "$type": "shadow"
        }
      }
    },
    "size": {
      "circle": {
        "20": {
          "height": {
            "$value": "{sz.xs}",
            "$type": "sizing"
          },
          "width": {
            "$value": "{sz.xs}",
            "$type": "sizing"
          },
          "radius": {
            "$value": "{br.full}",
            "$type": "borderRadius"
          },
          "border": {
            "$value": "{bw.sm}",
            "$type": "borderWidth"
          },
          "gap": {
            "$value": "{sp.none}",
            "$type": "spacing"
          },
          "sp-top": {
            "$value": "{sp.none}",
            "$type": "spacing"
          },
          "sp-right": {
            "$value": "{sp.none}",
            "$type": "spacing"
          },
          "sp-bottom": {
            "$value": "{sp.none}",
            "$type": "spacing"
          },
          "sp-left": {
            "$value": "{sp.none}",
            "$type": "spacing"
          },
          "icon": {
            "$value": "{sz.2xs}",
            "$type": "sizing"
          },
          "typography": {
            "$value": "{tp.label.xs.regular}",
            "$type": "typography"
          }
        },
        "24": {
          "height": {
            "$value": "{sz.sm}",
            "$type": "sizing"
          },
          "width": {
            "$value": "{sz.sm}",
            "$type": "sizing"
          },
          "radius": {
            "$value": "{br.full}",
            "$type": "borderRadius"
          },
          "border": {
            "$value": "{bw.sm}",
            "$type": "borderWidth"
          },
          "gap": {
            "$value": "{sp.none}",
            "$type": "spacing"
          },
          "sp-top": {
            "$value": "{sp.none}",
            "$type": "spacing"
          },
          "sp-right": {
            "$value": "{sp.none}",
            "$type": "spacing"
          },
          "sp-bottom": {
            "$value": "{sp.none}",
            "$type": "spacing"
          },
          "sp-left": {
            "$value": "{sp.none}",
            "$type": "spacing"
          },
          "icon": {
            "$value": "{sz.2xs}",
            "$type": "sizing"
          },
          "typography": {
            "$value": "{tp.label.xs.regular}",
            "$type": "typography"
          }
        },
        "28": {
          "height": {
            "$value": "{sz.md}",
            "$type": "sizing"
          },
          "width": {
            "$value": "{sz.md}",
            "$type": "sizing"
          },
          "radius": {
            "$value": "{br.full}",
            "$type": "borderRadius"
          },
          "border": {
            "$value": "{bw.sm}",
            "$type": "borderWidth"
          },
          "gap": {
            "$value": "{sp.none}",
            "$type": "spacing"
          },
          "sp-top": {
            "$value": "{sp.none}",
            "$type": "spacing"
          },
          "sp-right": {
            "$value": "{sp.none}",
            "$type": "spacing"
          },
          "sp-bottom": {
            "$value": "{sp.none}",
            "$type": "spacing"
          },
          "sp-left": {
            "$value": "{sp.none}",
            "$type": "spacing"
          },
          "icon": {
            "$value": "{sz.xs}",
            "$type": "sizing"
          },
          "typography": {
            "$value": "{tp.label.xs.regular}",
            "$type": "typography"
          }
        },
        "32": {
          "height": {
            "$value": "{sz.lg}",
            "$type": "sizing"
          },
          "width": {
            "$value": "{sz.lg}",
            "$type": "sizing"
          },
          "radius": {
            "$value": "{br.full}",
            "$type": "borderRadius"
          },
          "border": {
            "$value": "{bw.sm}",
            "$type": "borderWidth"
          },
          "gap": {
            "$value": "{sp.none}",
            "$type": "spacing"
          },
          "sp-top": {
            "$value": "{sp.none}",
            "$type": "spacing"
          },
          "sp-right": {
            "$value": "{sp.none}",
            "$type": "spacing"
          },
          "sp-bottom": {
            "$value": "{sp.none}",
            "$type": "spacing"
          },
          "sp-left": {
            "$value": "{sp.none}",
            "$type": "spacing"
          },
          "icon": {
            "$value": "{sz.xs}",
            "$type": "sizing"
          },
          "typography": {
            "$value": "{tp.label.xs.regular}",
            "$type": "typography"
          }
        },
        "36": {
          "height": {
            "$value": "{sz.xl}",
            "$type": "sizing"
          },
          "width": {
            "$value": "{sz.xl}",
            "$type": "sizing"
          },
          "radius": {
            "$value": "{br.full}",
            "$type": "borderRadius"
          },
          "border": {
            "$value": "{bw.sm}",
            "$type": "borderWidth"
          },
          "gap": {
            "$value": "{sp.none}",
            "$type": "spacing"
          },
          "sp-top": {
            "$value": "{sp.none}",
            "$type": "spacing"
          },
          "sp-right": {
            "$value": "{sp.none}",
            "$type": "spacing"
          },
          "sp-bottom": {
            "$value": "{sp.none}",
            "$type": "spacing"
          },
          "sp-left": {
            "$value": "{sp.none}",
            "$type": "spacing"
          },
          "icon": {
            "$value": "{sz.sm}",
            "$type": "sizing"
          },
          "typography": {
            "$value": "{tp.label.sm.regular}",
            "$type": "typography"
          }
        },
        "40": {
          "height": {
            "$value": "{sz.2xl}",
            "$type": "sizing"
          },
          "width": {
            "$value": "{sz.2xl}",
            "$type": "sizing"
          },
          "radius": {
            "$value": "{br.full}",
            "$type": "borderRadius"
          },
          "border": {
            "$value": "{bw.sm}",
            "$type": "borderWidth"
          },
          "gap": {
            "$value": "{sp.none}",
            "$type": "spacing"
          },
          "sp-top": {
            "$value": "{sp.none}",
            "$type": "spacing"
          },
          "sp-right": {
            "$value": "{sp.none}",
            "$type": "spacing"
          },
          "sp-bottom": {
            "$value": "{sp.none}",
            "$type": "spacing"
          },
          "sp-left": {
            "$value": "{sp.none}",
            "$type": "spacing"
          },
          "icon": {
            "$value": "{sz.sm}",
            "$type": "sizing"
          },
          "typography": {
            "$value": "{tp.label.md.regular}",
            "$type": "typography"
          }
        },
        "48": {
          "height": {
            "$value": "{sz.big.xs}",
            "$type": "sizing"
          },
          "width": {
            "$value": "{sz.big.xs}",
            "$type": "sizing"
          },
          "radius": {
            "$value": "{br.full}",
            "$type": "borderRadius"
          },
          "border": {
            "$value": "{bw.sm}",
            "$type": "borderWidth"
          },
          "gap": {
            "$value": "{sp.none}",
            "$type": "spacing"
          },
          "sp-top": {
            "$value": "{sp.none}",
            "$type": "spacing"
          },
          "sp-right": {
            "$value": "{sp.none}",
            "$type": "spacing"
          },
          "sp-bottom": {
            "$value": "{sp.none}",
            "$type": "spacing"
          },
          "sp-left": {
            "$value": "{sp.none}",
            "$type": "spacing"
          },
          "icon": {
            "$value": "{sz.sm}",
            "$type": "sizing"
          },
          "typography": {
            "$value": "{tp.label.md.regular}",
            "$type": "typography"
          }
        },
        "56": {
          "height": {
            "$value": "{sz.big.sm}",
            "$type": "sizing"
          },
          "width": {
            "$value": "{sz.big.sm}",
            "$type": "sizing"
          },
          "radius": {
            "$value": "{br.full}",
            "$type": "borderRadius"
          },
          "border": {
            "$value": "{bw.sm}",
            "$type": "borderWidth"
          },
          "gap": {
            "$value": "{sp.none}",
            "$type": "spacing"
          },
          "sp-top": {
            "$value": "{sp.none}",
            "$type": "spacing"
          },
          "sp-right": {
            "$value": "{sp.none}",
            "$type": "spacing"
          },
          "sp-bottom": {
            "$value": "{sp.none}",
            "$type": "spacing"
          },
          "sp-left": {
            "$value": "{sp.none}",
            "$type": "spacing"
          },
          "icon": {
            "$value": "{sz.sm}",
            "$type": "sizing"
          },
          "typography": {
            "$value": "{tp.label.lg.regular}",
            "$type": "typography"
          }
        },
        "64": {
          "height": {
            "$value": "{sz.big.md}",
            "$type": "sizing"
          },
          "width": {
            "$value": "{sz.big.md}",
            "$type": "sizing"
          },
          "radius": {
            "$value": "{br.full}",
            "$type": "borderRadius"
          },
          "border": {
            "$value": "{bw.sm}",
            "$type": "borderWidth"
          },
          "gap": {
            "$value": "{sp.none}",
            "$type": "spacing"
          },
          "sp-top": {
            "$value": "{sp.none}",
            "$type": "spacing"
          },
          "sp-right": {
            "$value": "{sp.none}",
            "$type": "spacing"
          },
          "sp-bottom": {
            "$value": "{sp.none}",
            "$type": "spacing"
          },
          "sp-left": {
            "$value": "{sp.none}",
            "$type": "spacing"
          },
          "icon": {
            "$value": "{sz.sm}",
            "$type": "sizing"
          },
          "typography": {
            "$value": "{tp.label.lg.regular}",
            "$type": "typography"
          }
        },
        "72": {
          "height": {
            "$value": "{sz.big.lg}",
            "$type": "sizing"
          },
          "width": {
            "$value": "{sz.big.lg}",
            "$type": "sizing"
          },
          "radius": {
            "$value": "{br.full}",
            "$type": "borderRadius"
          },
          "border": {
            "$value": "{bw.sm}",
            "$type": "borderWidth"
          },
          "gap": {
            "$value": "{sp.none}",
            "$type": "spacing"
          },
          "sp-top": {
            "$value": "{sp.none}",
            "$type": "spacing"
          },
          "sp-right": {
            "$value": "{sp.none}",
            "$type": "spacing"
          },
          "sp-bottom": {
            "$value": "{sp.none}",
            "$type": "spacing"
          },
          "sp-left": {
            "$value": "{sp.none}",
            "$type": "spacing"
          },
          "icon": {
            "$value": "{sz.sm}",
            "$type": "sizing"
          },
          "typography": {
            "$value": "{tp.title.md.regular}",
            "$type": "typography"
          }
        },
        "80": {
          "height": {
            "$value": "{sz.big.xl}",
            "$type": "sizing"
          },
          "width": {
            "$value": "{sz.big.xl}",
            "$type": "sizing"
          },
          "radius": {
            "$value": "{br.full}",
            "$type": "borderRadius"
          },
          "border": {
            "$value": "{bw.sm}",
            "$type": "borderWidth"
          },
          "gap": {
            "$value": "{sp.none}",
            "$type": "spacing"
          },
          "sp-top": {
            "$value": "{sp.none}",
            "$type": "spacing"
          },
          "sp-right": {
            "$value": "{sp.none}",
            "$type": "spacing"
          },
          "sp-bottom": {
            "$value": "{sp.none}",
            "$type": "spacing"
          },
          "sp-left": {
            "$value": "{sp.none}",
            "$type": "spacing"
          },
          "icon": {
            "$value": "{sz.sm}",
            "$type": "sizing"
          },
          "typography": {
            "$value": "{tp.title.md.regular}",
            "$type": "typography"
          }
        }
      },
      "square": {
        "20": {
          "height": {
            "$value": "{sz.xs}",
            "$type": "sizing"
          },
          "width": {
            "$value": "{sz.xs}",
            "$type": "sizing"
          },
          "radius": {
            "$value": "{br.xs}",
            "$type": "borderRadius"
          },
          "border": {
            "$value": "{bw.sm}",
            "$type": "borderWidth"
          },
          "gap": {
            "$value": "{sp.none}",
            "$type": "spacing"
          },
          "sp-top": {
            "$value": "{sp.none}",
            "$type": "spacing"
          },
          "sp-right": {
            "$value": "{sp.none}",
            "$type": "spacing"
          },
          "sp-bottom": {
            "$value": "{sp.none}",
            "$type": "spacing"
          },
          "sp-left": {
            "$value": "{sp.none}",
            "$type": "spacing"
          },
          "icon": {
            "$value": "{sz.2xs}",
            "$type": "sizing"
          },
          "typography": {
            "$value": "{tp.label.xs.regular}",
            "$type": "typography"
          }
        },
        "24": {
          "height": {
            "$value": "{sz.sm}",
            "$type": "sizing"
          },
          "width": {
            "$value": "{sz.sm}",
            "$type": "sizing"
          },
          "radius": {
            "$value": "{br.sm}",
            "$type": "borderRadius"
          },
          "border": {
            "$value": "{bw.sm}",
            "$type": "borderWidth"
          },
          "gap": {
            "$value": "{sp.none}",
            "$type": "spacing"
          },
          "sp-top": {
            "$value": "{sp.none}",
            "$type": "spacing"
          },
          "sp-right": {
            "$value": "{sp.none}",
            "$type": "spacing"
          },
          "sp-bottom": {
            "$value": "{sp.none}",
            "$type": "spacing"
          },
          "sp-left": {
            "$value": "{sp.none}",
            "$type": "spacing"
          },
          "icon": {
            "$value": "{sz.2xs}",
            "$type": "sizing"
          },
          "typography": {
            "$value": "{tp.label.xs.regular}",
            "$type": "typography"
          }
        },
        "28": {
          "height": {
            "$value": "{sz.md}",
            "$type": "sizing"
          },
          "width": {
            "$value": "{sz.md}",
            "$type": "sizing"
          },
          "radius": {
            "$value": "{br.md}",
            "$type": "borderRadius"
          },
          "border": {
            "$value": "{bw.sm}",
            "$type": "borderWidth"
          },
          "gap": {
            "$value": "{sp.none}",
            "$type": "spacing"
          },
          "sp-top": {
            "$value": "{sp.none}",
            "$type": "spacing"
          },
          "sp-right": {
            "$value": "{sp.none}",
            "$type": "spacing"
          },
          "sp-bottom": {
            "$value": "{sp.none}",
            "$type": "spacing"
          },
          "sp-left": {
            "$value": "{sp.none}",
            "$type": "spacing"
          },
          "icon": {
            "$value": "{sz.xs}",
            "$type": "sizing"
          },
          "typography": {
            "$value": "{tp.label.xs.regular}",
            "$type": "typography"
          }
        },
        "32": {
          "height": {
            "$value": "{sz.lg}",
            "$type": "sizing"
          },
          "width": {
            "$value": "{sz.lg}",
            "$type": "sizing"
          },
          "radius": {
            "$value": "{br.lg}",
            "$type": "borderRadius"
          },
          "border": {
            "$value": "{bw.sm}",
            "$type": "borderWidth"
          },
          "gap": {
            "$value": "{sp.none}",
            "$type": "spacing"
          },
          "sp-top": {
            "$value": "{sp.none}",
            "$type": "spacing"
          },
          "sp-right": {
            "$value": "{sp.none}",
            "$type": "spacing"
          },
          "sp-bottom": {
            "$value": "{sp.none}",
            "$type": "spacing"
          },
          "sp-left": {
            "$value": "{sp.none}",
            "$type": "spacing"
          },
          "icon": {
            "$value": "{sz.xs}",
            "$type": "sizing"
          },
          "typography": {
            "$value": "{tp.label.xs.regular}",
            "$type": "typography"
          }
        },
        "36": {
          "height": {
            "$value": "{sz.xl}",
            "$type": "sizing"
          },
          "width": {
            "$value": "{sz.xl}",
            "$type": "sizing"
          },
          "radius": {
            "$value": "{br.xl}",
            "$type": "borderRadius"
          },
          "border": {
            "$value": "{bw.sm}",
            "$type": "borderWidth"
          },
          "gap": {
            "$value": "{sp.none}",
            "$type": "spacing"
          },
          "sp-top": {
            "$value": "{sp.none}",
            "$type": "spacing"
          },
          "sp-right": {
            "$value": "{sp.none}",
            "$type": "spacing"
          },
          "sp-bottom": {
            "$value": "{sp.none}",
            "$type": "spacing"
          },
          "sp-left": {
            "$value": "{sp.none}",
            "$type": "spacing"
          },
          "icon": {
            "$value": "{sz.sm}",
            "$type": "sizing"
          },
          "typography": {
            "$value": "{tp.label.sm.regular}",
            "$type": "typography"
          }
        },
        "40": {
          "height": {
            "$value": "{sz.2xl}",
            "$type": "sizing"
          },
          "width": {
            "$value": "{sz.2xl}",
            "$type": "sizing"
          },
          "radius": {
            "$value": "{br.big.3xs}",
            "$type": "borderRadius"
          },
          "border": {
            "$value": "{bw.sm}",
            "$type": "borderWidth"
          },
          "gap": {
            "$value": "{sp.none}",
            "$type": "spacing"
          },
          "sp-top": {
            "$value": "{sp.none}",
            "$type": "spacing"
          },
          "sp-right": {
            "$value": "{sp.none}",
            "$type": "spacing"
          },
          "sp-bottom": {
            "$value": "{sp.none}",
            "$type": "spacing"
          },
          "sp-left": {
            "$value": "{sp.none}",
            "$type": "spacing"
          },
          "icon": {
            "$value": "{sz.sm}",
            "$type": "sizing"
          },
          "typography": {
            "$value": "{tp.label.md.regular}",
            "$type": "typography"
          }
        },
        "48": {
          "height": {
            "$value": "{sz.big.xs}",
            "$type": "sizing"
          },
          "width": {
            "$value": "{sz.big.xs}",
            "$type": "sizing"
          },
          "radius": {
            "$value": "{br.big.3xs}",
            "$type": "borderRadius"
          },
          "border": {
            "$value": "{bw.sm}",
            "$type": "borderWidth"
          },
          "gap": {
            "$value": "{sp.none}",
            "$type": "spacing"
          },
          "sp-top": {
            "$value": "{sp.none}",
            "$type": "spacing"
          },
          "sp-right": {
            "$value": "{sp.none}",
            "$type": "spacing"
          },
          "sp-bottom": {
            "$value": "{sp.none}",
            "$type": "spacing"
          },
          "sp-left": {
            "$value": "{sp.none}",
            "$type": "spacing"
          },
          "icon": {
            "$value": "{sz.sm}",
            "$type": "sizing"
          },
          "typography": {
            "$value": "{tp.label.md.regular}",
            "$type": "typography"
          }
        },
        "56": {
          "height": {
            "$value": "{sz.big.sm}",
            "$type": "sizing"
          },
          "width": {
            "$value": "{sz.big.sm}",
            "$type": "sizing"
          },
          "radius": {
            "$value": "{br.big.3xs}",
            "$type": "borderRadius"
          },
          "border": {
            "$value": "{bw.sm}",
            "$type": "borderWidth"
          },
          "gap": {
            "$value": "{sp.none}",
            "$type": "spacing"
          },
          "sp-top": {
            "$value": "{sp.none}",
            "$type": "spacing"
          },
          "sp-right": {
            "$value": "{sp.none}",
            "$type": "spacing"
          },
          "sp-bottom": {
            "$value": "{sp.none}",
            "$type": "spacing"
          },
          "sp-left": {
            "$value": "{sp.none}",
            "$type": "spacing"
          },
          "icon": {
            "$value": "{sz.sm}",
            "$type": "sizing"
          },
          "typography": {
            "$value": "{tp.label.lg.regular}",
            "$type": "typography"
          }
        },
        "64": {
          "height": {
            "$value": "{sz.big.md}",
            "$type": "sizing"
          },
          "width": {
            "$value": "{sz.big.md}",
            "$type": "sizing"
          },
          "radius": {
            "$value": "{br.big.3xs}",
            "$type": "borderRadius"
          },
          "border": {
            "$value": "{bw.sm}",
            "$type": "borderWidth"
          },
          "gap": {
            "$value": "{sp.none}",
            "$type": "spacing"
          },
          "sp-top": {
            "$value": "{sp.none}",
            "$type": "spacing"
          },
          "sp-right": {
            "$value": "{sp.none}",
            "$type": "spacing"
          },
          "sp-bottom": {
            "$value": "{sp.none}",
            "$type": "spacing"
          },
          "sp-left": {
            "$value": "{sp.none}",
            "$type": "spacing"
          },
          "icon": {
            "$value": "{sz.sm}",
            "$type": "sizing"
          },
          "typography": {
            "$value": "{tp.label.lg.regular}",
            "$type": "typography"
          }
        },
        "72": {
          "height": {
            "$value": "{sz.big.lg}",
            "$type": "sizing"
          },
          "width": {
            "$value": "{sz.big.lg}",
            "$type": "sizing"
          },
          "radius": {
            "$value": "{br.big.3xs}",
            "$type": "borderRadius"
          },
          "border": {
            "$value": "{bw.sm}",
            "$type": "borderWidth"
          },
          "gap": {
            "$value": "{sp.none}",
            "$type": "spacing"
          },
          "sp-top": {
            "$value": "{sp.none}",
            "$type": "spacing"
          },
          "sp-right": {
            "$value": "{sp.none}",
            "$type": "spacing"
          },
          "sp-bottom": {
            "$value": "{sp.none}",
            "$type": "spacing"
          },
          "sp-left": {
            "$value": "{sp.none}",
            "$type": "spacing"
          },
          "icon": {
            "$value": "{sz.sm}",
            "$type": "sizing"
          },
          "typography": {
            "$value": "{tp.title.md.regular}",
            "$type": "typography"
          }
        },
        "80": {
          "height": {
            "$value": "{sz.big.xl}",
            "$type": "sizing"
          },
          "width": {
            "$value": "{sz.big.xl}",
            "$type": "sizing"
          },
          "radius": {
            "$value": "{br.big.3xs}",
            "$type": "borderRadius"
          },
          "border": {
            "$value": "{bw.sm}",
            "$type": "borderWidth"
          },
          "gap": {
            "$value": "{sp.none}",
            "$type": "spacing"
          },
          "sp-top": {
            "$value": "{sp.none}",
            "$type": "spacing"
          },
          "sp-right": {
            "$value": "{sp.none}",
            "$type": "spacing"
          },
          "sp-bottom": {
            "$value": "{sp.none}",
            "$type": "spacing"
          },
          "sp-left": {
            "$value": "{sp.none}",
            "$type": "spacing"
          },
          "icon": {
            "$value": "{sz.sm}",
            "$type": "sizing"
          },
          "typography": {
            "$value": "{tp.title.md.regular}",
            "$type": "typography"
          }
        }
      }
    }
  }
}
